mxproc/__init__.py
mxproc/command.py
mxproc/common.py
mxproc/log.py
mxproc/xtal.py
mxproc/engines/__init__.py
mxproc/engines/dials/__init__.py
mxproc/engines/dials/parser.py
mxproc/engines/dials/data/spots.yml
mxproc/engines/xds/__init__.py
mxproc/engines/xds/indexing.py
mxproc/engines/xds/io.py
mxproc/engines/xds/stats.py
mxproc/engines/xds/parser/__init__.py
mxproc/engines/xds/parser/pointless.py
mxproc/engines/xds/parser/data/correct.yml
mxproc/engines/xds/parser/data/idxref.yml
mxproc/engines/xds/parser/data/integrate.yml
mxproc/engines/xds/parser/data/spots.yml
mxproc/engines/xds/parser/data/xdsstat.yml
mxproc/engines/xds/parser/data/xparm.yml
mxproc/engines/xds/parser/data/xplan.yml
mxproc/engines/xds/parser/data/xscale.yml
mxproc/engines/xds/parser/data/xtriage.yml
mxproc/programs/__init__.py
mxproc/programs/raddose.py
mxproc/reporting/__init__.py
mxproc/reporting/generic.py
mxproc/reporting/screening.py
mxproc/reporting/text.py
mxproc/reporting/data/report.html
mxproc/reporting/data/report.js
mxproc/reporting/data/report.min.css
mxproc/reporting/data/report.min.js
mxproc/reporting/data/report.scss
mxproc-2024.10.1.data/scripts/auto.index
mxproc-2024.10.1.data/scripts/auto.init
mxproc-2024.10.1.data/scripts/auto.integrate
mxproc-2024.10.1.data/scripts/auto.process
mxproc-2024.10.1.data/scripts/auto.scale
mxproc-2024.10.1.data/scripts/auto.spots
mxproc-2024.10.1.data/scripts/auto.strategy
mxproc-2024.10.1.data/scripts/auto.symmetry
mxproc-2024.10.1.data/scripts/auto.xds
mxproc-2024.10.1.dist-info/LICENSE
mxproc-2024.10.1.dist-info/METADATA
mxproc-2024.10.1.dist-info/WHEEL
mxproc-2024.10.1.dist-info/top_level.txt
mxproc-2024.10.1.dist-info/RECORD
