Metadata-Version: 2.1
Name: mxproc
Version: 2024.10.1
Summary: MX Automated Data Processing Pipeline
Author-email: Michel Fodje <michel4j@gmail.com>
License: MIT
Project-URL: Homepage, https://github.com/michel4j/mxproc
Keywords: Data Processing Pipeline,MX,AutoProcess
Classifier: License :: OSI Approved :: MIT License
Classifier: Programming Language :: Python :: 3
Classifier: Programming Language :: Python :: 3.9
Classifier: Programming Language :: Python :: 3.10
Classifier: Programming Language :: Python :: 3.11
Classifier: Programming Language :: Python :: 3.12
License-File: LICENSE
Requires-Dist: mxio
Requires-Dist: parsefire
Requires-Dist: matplotlib
Requires-Dist: numpy
Requires-Dist: pyyaml
Requires-Dist: tqdm
Requires-Dist: pandas
Requires-Dist: prettytable
Requires-Dist: vg
Requires-Dist: scipy
